{
  "category": "Heroes",
  "units": [

    {
      "id": "celestial_captain",
      "name": "Celestial Captain",
      "profile": {
        "points": 65
      },
      "magicItemLimit": 50,
      "options": [
        {
          "name": "Battle Standard",
          "cost": 25
        },
        {
          "group": "Melee Weapon",
          "choices": [
            { "name": "Additional hand weapon", "cost": 2 },
            { "name": "Celestial blade", "cost": 2 },
            { "name": "Spear", "cost": 2 },
            { "name": "Light lance", "cost": 3 },
            { "name": "Polearm", "cost": 6 },
            { "name": "Great weapon", "cost": 9 }
          ]
        },
        {
          "group": "Ranged Weapon",
          "choices": [
            { "name": "Bow", "cost": 5 },
            { "name": "Crossbow", "cost": 7 },
            { "name": "Repeater crossbow", "cost": 6 },
            { "name": "Handgun", "cost": 7 },
            { "name": "Dragon fire pistol", "cost": 9 }
          ]
        },
        {
          "group": "Armour",
          "choices": [
            { "name": "Heavy armour", "cost": 6 },
            { "name": "Shield", "cost": 2 }
          ]
        }
      ],
      "mounts": [
        { "name": "Warhorse", "cost": 12 },
        { "name": "Jade Longma", "cost": 32 },
        { "name": "War Chariot (replacing one of the crew)", "cost": 70 }
      ]
    },

    {
      "id": "gate_master",
      "name": "Gate Master",
      "profile": {
        "points": 45
      },
      "magicItemLimit": 50,
      "options": [
        {
          "name": "Battle Standard",
          "cost": 25
        },
        {
          "group": "Melee Weapon",
          "choices": [
            { "name": "Additional hand weapon", "cost": 2 },
            { "name": "Celestial blade", "cost": 2 },
            { "name": "Spear", "cost": 2 },
            { "name": "Light lance", "cost": 2 },
            { "name": "Polearm", "cost": 4 },
            { "name": "Great weapon", "cost": 6 }
          ]
        },
        {
          "group": "Ranged Weapon",
          "choices": [
            { "name": "Bow", "cost": 4 },
            { "name": "Repeater crossbow", "cost": 5 },
            { "name": "Crossbow", "cost": 6 },
            { "name": "Handgun", "cost": 6 }
          ]
        },
        {
          "group": "Armour",
          "choices": [
            { "name": "Shield", "cost": 2 }
          ]
        }
      ],
      "mounts": [
        { "name": "Warhorse", "cost": 12 }
      ]
    },

    {
      "id": "alchemist",
      "name": "Alchemist",
      "profile": {
        "points": 65
      },
      "magicItemLimit": 50,
      "options": [
        {
          "name": "Upgrade to Wizard Level 2",
          "cost": 35
        },
        {
          "group": "Additional Equipment",
          "choices": [
            { "name": "Light armour", "cost": 2 }
          ]
        }
      ],
      "mounts": [
        { "name": "Warhorse", "cost": 12 }
      ]
    },

    {
      "id": "astromancer",
      "name": "Astromancer",
      "profile": {
        "points": 65
      },
      "magicItemLimit": 50,
      "options": [
        {
          "name": "Upgrade to Wizard Level 2",
          "cost": 35
        },
        {
          "group": "Additional Equipment",
          "choices": [
            { "name": "Light armour", "cost": 2 }
          ]
        }
      ],
      "mounts": [
        { "name": "Warhorse", "cost": 12 },
        { "name": "Wu Xing War Compass (replacing the Apprentice Astromancer)", "cost": 120 }
      ]
    },

    {
      "id": "magistrate",
      "name": "Magistrate",
      "profile": {
        "points": 50
      },
      "magicItemLimit": 50,
      "options": [
        {
          "group": "Additional Equipment",
          "choices": [
            { "name": "Dragon fire bombs", "cost": 9 },
            { "name": "Light armour", "cost": 2 }
          ]
        }
      ],
      "mounts": [
        { "name": "Warhorse", "cost": 12 },
        { "name": "Sky Lantern (replacing one of the crew)", "cost": 85 }
      ]
    },

    {
      "id": "blademaster",
      "name": "Blademaster",
      "profile": {
        "points": 120
      },
      "magicItemLimit": 50,
      "options": [
        {
          "group": "Melee Weapon",
          "choices": [
            { "name": "Additional hand weapon", "cost": 2 },
            { "name": "Spear", "cost": 3 },
            { "name": "Polearm", "cost": 6 },
            { "name": "Great weapon", "cost": 9 }
          ]
        },
        {
          "group": "Additional Equipment",
          "choices": [
            { "name": "Light armour", "cost": 2 }
          ]
        }
      ]
    }

  ]
}
